dzcode/__init__.py
dzcode/core.py
dzcode-0.0.2.dist-info/licenses/LICENSE
dzcode-0.0.2.dist-info/METADATA
dzcode-0.0.2.dist-info/WHEEL
dzcode-0.0.2.dist-info/top_level.txt
dzcode-0.0.2.dist-info/RECORD
