Metadata-Version: 2.4
Name: dzcode
Version: 0.0.2
Summary: </DZ C0de> Helper Package
Author-email: msdzulqurnain <msdzulqurnain@gmail.com>
License-Expression: MIT
Project-URL: Homepage, https://github.com/msdzulqurnain/dzcode
Project-URL: Issues, https://github.com/msdzulqurnain/dzcode/issues
Keywords: python,dzcode,helper,package,utils
Classifier: Programming Language :: Python :: 3
Classifier: Operating System :: OS Independent
Requires-Python: >=3.8
License-File: LICENSE
Dynamic: license-file
